maze_generator/__init__.py
maze_generator/core.py
maze_generator_for_algorithm-0.2.0.dist-info/licenses/LICENSE
maze_generator_for_algorithm-0.2.0.dist-info/METADATA
maze_generator_for_algorithm-0.2.0.dist-info/WHEEL
maze_generator_for_algorithm-0.2.0.dist-info/top_level.txt
maze_generator_for_algorithm-0.2.0.dist-info/RECORD
