Metadata-Version: 2.4
Name: maze_generator_for_algorithm
Version: 0.2.0
Summary: Maze generation tool with turtle graphics and JSON override support.
Author: Chandramouli Ramesh
Author-email: aravind2377@gmail.com
Classifier: Programming Language :: Python :: 3
Classifier: License :: OSI Approved :: MIT License
Requires-Python: >=3.7
License-File: LICENSE
Requires-Dist: pyautogui
Requires-Dist: Pillow
Dynamic: author
Dynamic: author-email
Dynamic: classifier
Dynamic: description
Dynamic: description-content-type
Dynamic: license-file
Dynamic: requires-dist
Dynamic: requires-python
Dynamic: summary
